api_deploy/__init__.py
api_deploy/cli.py
api_deploy/client.py
api_deploy/config.py
api_deploy/converters.py
api_deploy/schema.py
api_deploy/processors/__init__.py
api_deploy/processors/abstract_processor.py
api_deploy/processors/code_generator.py
api_deploy/processors/strict_processor.py
api_deploy/processors/templates/typescript.compound.jinja2
api_deploy/processors/templates/typescript.jinja2
api_deploy/processors/templates/typescript.object.jinja2
api_deploy-0.17.0.dist-info/METADATA
api_deploy-0.17.0.dist-info/WHEEL
api_deploy-0.17.0.dist-info/entry_points.txt
api_deploy-0.17.0.dist-info/top_level.txt
api_deploy-0.17.0.dist-info/RECORD
