Metadata-Version: 2.1
Name: api-deploy
Version: 0.17.0
Summary: Manage Amazon REST API Gateway deployments
Home-page: https://github.com/fabfuel/api-deploy
Author: Fabian Fuelling
Author-email: pypi@fabfuel.de
License: BSD-3-Clause
Download-URL: https://github.com/fabfuel/api-deploy/archive/0.17.0.tar.gz
Platform: any
Classifier: Environment :: Console
Classifier: Intended Audience :: Developers
Classifier: License :: OSI Approved :: BSD License
Classifier: Operating System :: POSIX
Classifier: Operating System :: MacOS
Classifier: Operating System :: Unix
Classifier: Programming Language :: Python
Classifier: Programming Language :: Python :: 3
Classifier: Topic :: Software Development :: Libraries :: Python Modules
Requires-Dist: click (<9,>=8.1.3)
Requires-Dist: mergedeep (>=1.3.4)
Requires-Dist: boto3 (>=1.26.118)
Requires-Dist: PyYAML (>=6.0)
Requires-Dist: requests (>=2.31.0)
Requires-Dist: Jinja2 (==3.1.2)
Requires-Dist: urllib3 (<2)
